[
    {
        "id": 1,
        "product_id": "699",
        "date": "2023-09-26",
        "price": 1.89
    },
    {
        "id": 2,
        "product_id": "699",
        "date": "2023-09-25",
        "price": 1.03
    },
    {
        "id": 3,
        "product_id": "699",
        "date": "2023-09-28",
        "price": 1.33
    },
    {
        "id": 4,
        "product_id": "699",
        "date": "2023-09-27",
        "price": 0.64
    },
    {
        "id": 5,
        "product_id": "699",
        "date": "2023-09-29",
        "price": 0.84
    },
    {
        "id": 6,
        "product_id": "699",
        "date": "2023-09-24",
        "price": 1.82
    },
    {
        "id": 7,
        "product_id": "699",
        "date": "2023-09-30",
        "price": 3.26
    },
    {
        "id": 8,
        "product_id": "896",
        "date": "2023-09-26",
        "price": 4.42
    },
    {
        "id": 9,
        "product_id": "896",
        "date": "2023-09-25",
        "price": 4.23
    },
    {
        "id": 10,
        "product_id": "896",
        "date": "2023-09-28",
        "price": 2.1
    },
    {
        "id": 11,
        "product_id": "896",
        "date": "2023-09-27",
        "price": 2.54
    },
    {
        "id": 12,
        "product_id": "896",
        "date": "2023-09-29",
        "price": 3.35
    },
    {
        "id": 13,
        "product_id": "896",
        "date": "2023-09-24",
        "price": 3.35
    },
    {
        "id": 14,
        "product_id": "896",
        "date": "2023-09-30",
        "price": 3.94
    },
    {
        "id": 15,
        "product_id": "1085",
        "date": "2023-09-26",
        "price": 1.73
    },
    {
        "id": 16,
        "product_id": "1085",
        "date": "2023-09-25",
        "price": 0.91
    },
    {
        "id": 17,
        "product_id": "1085",
        "date": "2023-09-28",
        "price": 0.6
    },
    {
        "id": 18,
        "product_id": "1085",
        "date": "2023-09-27",
        "price": 2.29
    },
    {
        "id": 19,
        "product_id": "1085",
        "date": "2023-09-29",
        "price": 3.39
    },
    {
        "id": 20,
        "product_id": "1085",
        "date": "2023-09-24",
        "price": 3.44
    },
    {
        "id": 21,
        "product_id": "1085",
        "date": "2023-09-30",
        "price": 2.95
    },
    {
        "id": 22,
        "product_id": "1132",
        "date": "2023-09-26",
        "price": 4.18
    },
    {
        "id": 23,
        "product_id": "1132",
        "date": "2023-09-25",
        "price": 0.59
    },
    {
        "id": 24,
        "product_id": "1132",
        "date": "2023-09-28",
        "price": 3.13
    },
    {
        "id": 25,
        "product_id": "1132",
        "date": "2023-09-27",
        "price": 2.54
    },
    {
        "id": 26,
        "product_id": "1132",
        "date": "2023-09-29",
        "price": 0.51
    },
    {
        "id": 27,
        "product_id": "1132",
        "date": "2023-09-24",
        "price": 2.33
    },
    {
        "id": 28,
        "product_id": "1132",
        "date": "2023-09-30",
        "price": 2.61
    },
    {
        "id": 29,
        "product_id": "1154",
        "date": "2023-09-26",
        "price": 2.38
    },
    {
        "id": 30,
        "product_id": "1154",
        "date": "2023-09-25",
        "price": 1.16
    },
    {
        "id": 31,
        "product_id": "1154",
        "date": "2023-09-28",
        "price": 1.7
    },
    {
        "id": 32,
        "product_id": "1154",
        "date": "2023-09-27",
        "price": 2.52
    },
    {
        "id": 33,
        "product_id": "1154",
        "date": "2023-09-29",
        "price": 2.63
    },
    {
        "id": 34,
        "product_id": "1154",
        "date": "2023-09-24",
        "price": 0.85
    },
    {
        "id": 35,
        "product_id": "1154",
        "date": "2023-09-30",
        "price": 3.24
    },
    {
        "id": 36,
        "product_id": "774",
        "date": "2023-09-26",
        "price": 2.37
    },
    {
        "id": 37,
        "product_id": "774",
        "date": "2023-09-25",
        "price": 0.75
    },
    {
        "id": 38,
        "product_id": "774",
        "date": "2023-09-28",
        "price": 1.22
    },
    {
        "id": 39,
        "product_id": "774",
        "date": "2023-09-27",
        "price": 0.87
    },
    {
        "id": 40,
        "product_id": "774",
        "date": "2023-09-29",
        "price": 3.86
    },
    {
        "id": 41,
        "product_id": "774",
        "date": "2023-09-24",
        "price": 0.85
    },
    {
        "id": 42,
        "product_id": "774",
        "date": "2023-09-30",
        "price": 4.22
    },
    {
        "id": 43,
        "product_id": "897",
        "date": "2023-09-26",
        "price": 3.44
    },
    {
        "id": 44,
        "product_id": "897",
        "date": "2023-09-25",
        "price": 4.48
    },
    {
        "id": 45,
        "product_id": "897",
        "date": "2023-09-28",
        "price": 2.96
    },
    {
        "id": 46,
        "product_id": "897",
        "date": "2023-09-27",
        "price": 2.38
    },
    {
        "id": 47,
        "product_id": "897",
        "date": "2023-09-29",
        "price": 2.72
    },
    {
        "id": 48,
        "product_id": "897",
        "date": "2023-09-24",
        "price": 1.67
    },
    {
        "id": 49,
        "product_id": "897",
        "date": "2023-09-30",
        "price": 0.87
    },
    {
        "id": 50,
        "product_id": "930",
        "date": "2023-09-26",
        "price": 4.16
    },
    {
        "id": 51,
        "product_id": "930",
        "date": "2023-09-25",
        "price": 4.33
    },
    {
        "id": 52,
        "product_id": "930",
        "date": "2023-09-28",
        "price": 1.44
    },
    {
        "id": 53,
        "product_id": "930",
        "date": "2023-09-27",
        "price": 3.5
    },
    {
        "id": 54,
        "product_id": "930",
        "date": "2023-09-29",
        "price": 3.99
    },
    {
        "id": 55,
        "product_id": "930",
        "date": "2023-09-24",
        "price": 4.48
    },
    {
        "id": 56,
        "product_id": "930",
        "date": "2023-09-30",
        "price": 3.48
    },
    {
        "id": 57,
        "product_id": "1018",
        "date": "2023-09-26",
        "price": 4.25
    },
    {
        "id": 58,
        "product_id": "1018",
        "date": "2023-09-25",
        "price": 3.38
    },
    {
        "id": 59,
        "product_id": "1018",
        "date": "2023-09-28",
        "price": 2.04
    },
    {
        "id": 60,
        "product_id": "1018",
        "date": "2023-09-27",
        "price": 2.86
    },
    {
        "id": 61,
        "product_id": "1018",
        "date": "2023-09-29",
        "price": 3.09
    },
    {
        "id": 62,
        "product_id": "1018",
        "date": "2023-09-24",
        "price": 1.34
    },
    {
        "id": 63,
        "product_id": "1018",
        "date": "2023-09-30",
        "price": 1.94
    },
    {
        "id": 64,
        "product_id": "1110",
        "date": "2023-09-26",
        "price": 2.65
    },
    {
        "id": 65,
        "product_id": "1110",
        "date": "2023-09-25",
        "price": 3.93
    },
    {
        "id": 66,
        "product_id": "1110",
        "date": "2023-09-28",
        "price": 3.53
    },
    {
        "id": 67,
        "product_id": "1110",
        "date": "2023-09-27",
        "price": 3.14
    },
    {
        "id": 68,
        "product_id": "1110",
        "date": "2023-09-29",
        "price": 2.59
    },
    {
        "id": 69,
        "product_id": "1110",
        "date": "2023-09-24",
        "price": 2.04
    },
    {
        "id": 70,
        "product_id": "1110",
        "date": "2023-09-30",
        "price": 0.88
    },
    {
        "id": 71,
        "product_id": "978",
        "date": "2023-09-26",
        "price": 1.93
    },
    {
        "id": 72,
        "product_id": "978",
        "date": "2023-09-25",
        "price": 3.4
    },
    {
        "id": 73,
        "product_id": "978",
        "date": "2023-09-28",
        "price": 2.34
    },
    {
        "id": 74,
        "product_id": "978",
        "date": "2023-09-27",
        "price": 3.34
    },
    {
        "id": 75,
        "product_id": "978",
        "date": "2023-09-29",
        "price": 1.37
    },
    {
        "id": 76,
        "product_id": "978",
        "date": "2023-09-24",
        "price": 2.07
    },
    {
        "id": 77,
        "product_id": "978",
        "date": "2023-09-30",
        "price": 3.43
    },
    {
        "id": 78,
        "product_id": "980",
        "date": "2023-09-26",
        "price": 1.84
    },
    {
        "id": 79,
        "product_id": "980",
        "date": "2023-09-25",
        "price": 4.27
    },
    {
        "id": 80,
        "product_id": "980",
        "date": "2023-09-28",
        "price": 3.15
    },
    {
        "id": 81,
        "product_id": "980",
        "date": "2023-09-27",
        "price": 1.81
    },
    {
        "id": 82,
        "product_id": "980",
        "date": "2023-09-29",
        "price": 3.13
    },
    {
        "id": 83,
        "product_id": "980",
        "date": "2023-09-24",
        "price": 0.79
    },
    {
        "id": 84,
        "product_id": "980",
        "date": "2023-09-30",
        "price": 0.86
    },
    {
        "id": 85,
        "product_id": "1142",
        "date": "2023-09-26",
        "price": 2.57
    },
    {
        "id": 86,
        "product_id": "1142",
        "date": "2023-09-25",
        "price": 2.56
    },
    {
        "id": 87,
        "product_id": "1142",
        "date": "2023-09-28",
        "price": 2.29
    },
    {
        "id": 88,
        "product_id": "1142",
        "date": "2023-09-27",
        "price": 3.28
    },
    {
        "id": 89,
        "product_id": "1142",
        "date": "2023-09-29",
        "price": 4.46
    },
    {
        "id": 90,
        "product_id": "1142",
        "date": "2023-09-24",
        "price": 1.99
    },
    {
        "id": 91,
        "product_id": "1142",
        "date": "2023-09-30",
        "price": 3.45
    },
    {
        "id": 92,
        "product_id": "1201",
        "date": "2023-09-26",
        "price": 3.18
    },
    {
        "id": 93,
        "product_id": "1201",
        "date": "2023-09-25",
        "price": 1.88
    },
    {
        "id": 94,
        "product_id": "1201",
        "date": "2023-09-28",
        "price": 2.89
    },
    {
        "id": 95,
        "product_id": "1201",
        "date": "2023-09-27",
        "price": 2.37
    },
    {
        "id": 96,
        "product_id": "1201",
        "date": "2023-09-29",
        "price": 0.95
    },
    {
        "id": 97,
        "product_id": "1201",
        "date": "2023-09-24",
        "price": 3.7
    },
    {
        "id": 98,
        "product_id": "1201",
        "date": "2023-09-30",
        "price": 3.02
    },
    {
        "id": 99,
        "product_id": "1336",
        "date": "2023-09-26",
        "price": 0.94
    },
    {
        "id": 100,
        "product_id": "1336",
        "date": "2023-09-25",
        "price": 0.95
    },
    {
        "id": 101,
        "product_id": "1336",
        "date": "2023-09-28",
        "price": 0.51
    },
    {
        "id": 102,
        "product_id": "1336",
        "date": "2023-09-27",
        "price": 3.55
    },
    {
        "id": 103,
        "product_id": "1336",
        "date": "2023-09-29",
        "price": 3.66
    },
    {
        "id": 104,
        "product_id": "1336",
        "date": "2023-09-24",
        "price": 1.14
    },
    {
        "id": 105,
        "product_id": "1336",
        "date": "2023-09-30",
        "price": 2.84
    },
    {
        "id": 106,
        "product_id": "1060",
        "date": "2023-09-26",
        "price": 1.82
    },
    {
        "id": 107,
        "product_id": "1060",
        "date": "2023-09-25",
        "price": 4.14
    },
    {
        "id": 108,
        "product_id": "1060",
        "date": "2023-09-28",
        "price": 0.79
    },
    {
        "id": 109,
        "product_id": "1060",
        "date": "2023-09-27",
        "price": 3.15
    },
    {
        "id": 110,
        "product_id": "1060",
        "date": "2023-09-29",
        "price": 3.5
    },
    {
        "id": 111,
        "product_id": "1060",
        "date": "2023-09-24",
        "price": 3.6
    },
    {
        "id": 112,
        "product_id": "1060",
        "date": "2023-09-30",
        "price": 2.65
    },
    {
        "id": 113,
        "product_id": "1112",
        "date": "2023-09-26",
        "price": 4.06
    },
    {
        "id": 114,
        "product_id": "1112",
        "date": "2023-09-25",
        "price": 3.47
    },
    {
        "id": 115,
        "product_id": "1112",
        "date": "2023-09-28",
        "price": 3.1
    },
    {
        "id": 116,
        "product_id": "1112",
        "date": "2023-09-27",
        "price": 2.7
    },
    {
        "id": 117,
        "product_id": "1112",
        "date": "2023-09-29",
        "price": 4.23
    },
    {
        "id": 118,
        "product_id": "1112",
        "date": "2023-09-24",
        "price": 3.33
    },
    {
        "id": 119,
        "product_id": "1112",
        "date": "2023-09-30",
        "price": 2.66
    },
    {
        "id": 120,
        "product_id": "1224",
        "date": "2023-09-26",
        "price": 3.27
    },
    {
        "id": 121,
        "product_id": "1224",
        "date": "2023-09-25",
        "price": 2.98
    },
    {
        "id": 122,
        "product_id": "1224",
        "date": "2023-09-28",
        "price": 1.38
    },
    {
        "id": 123,
        "product_id": "1224",
        "date": "2023-09-27",
        "price": 3.73
    },
    {
        "id": 124,
        "product_id": "1224",
        "date": "2023-09-29",
        "price": 2.58
    },
    {
        "id": 125,
        "product_id": "1224",
        "date": "2023-09-24",
        "price": 0.98
    },
    {
        "id": 126,
        "product_id": "1224",
        "date": "2023-09-30",
        "price": 2.36
    },
    {
        "id": 127,
        "product_id": "1236",
        "date": "2023-09-26",
        "price": 0.76
    },
    {
        "id": 128,
        "product_id": "1236",
        "date": "2023-09-25",
        "price": 1.81
    },
    {
        "id": 129,
        "product_id": "1236",
        "date": "2023-09-28",
        "price": 4.48
    },
    {
        "id": 130,
        "product_id": "1236",
        "date": "2023-09-27",
        "price": 1.42
    },
    {
        "id": 131,
        "product_id": "1236",
        "date": "2023-09-29",
        "price": 4.42
    },
    {
        "id": 132,
        "product_id": "1236",
        "date": "2023-09-24",
        "price": 1.55
    },
    {
        "id": 133,
        "product_id": "1236",
        "date": "2023-09-30",
        "price": 2.98
    },
    {
        "id": 134,
        "product_id": "1260",
        "date": "2023-09-26",
        "price": 1.32
    },
    {
        "id": 135,
        "product_id": "1260",
        "date": "2023-09-25",
        "price": 3.5
    },
    {
        "id": 136,
        "product_id": "1260",
        "date": "2023-09-28",
        "price": 2.92
    },
    {
        "id": 137,
        "product_id": "1260",
        "date": "2023-09-27",
        "price": 2.35
    },
    {
        "id": 138,
        "product_id": "1260",
        "date": "2023-09-29",
        "price": 4.44
    },
    {
        "id": 139,
        "product_id": "1260",
        "date": "2023-09-24",
        "price": 1.07
    },
    {
        "id": 140,
        "product_id": "1260",
        "date": "2023-09-30",
        "price": 3.25
    },
    {
        "id": 141,
        "product_id": "379",
        "date": "2023-09-26",
        "price": 3.52
    },
    {
        "id": 142,
        "product_id": "379",
        "date": "2023-09-25",
        "price": 4.13
    },
    {
        "id": 143,
        "product_id": "379",
        "date": "2023-09-28",
        "price": 2.02
    },
    {
        "id": 144,
        "product_id": "379",
        "date": "2023-09-27",
        "price": 4.43
    },
    {
        "id": 145,
        "product_id": "379",
        "date": "2023-09-29",
        "price": 2.81
    },
    {
        "id": 146,
        "product_id": "379",
        "date": "2023-09-24",
        "price": 2.0
    },
    {
        "id": 147,
        "product_id": "379",
        "date": "2023-09-30",
        "price": 1.03
    },
    {
        "id": 148,
        "product_id": "414",
        "date": "2023-09-26",
        "price": 1.07
    },
    {
        "id": 149,
        "product_id": "414",
        "date": "2023-09-25",
        "price": 1.16
    },
    {
        "id": 150,
        "product_id": "414",
        "date": "2023-09-28",
        "price": 3.16
    },
    {
        "id": 151,
        "product_id": "414",
        "date": "2023-09-27",
        "price": 2.01
    },
    {
        "id": 152,
        "product_id": "414",
        "date": "2023-09-29",
        "price": 3.8
    },
    {
        "id": 153,
        "product_id": "414",
        "date": "2023-09-24",
        "price": 3.73
    },
    {
        "id": 154,
        "product_id": "414",
        "date": "2023-09-30",
        "price": 1.58
    },
    {
        "id": 155,
        "product_id": "516",
        "date": "2023-09-26",
        "price": 0.91
    },
    {
        "id": 156,
        "product_id": "516",
        "date": "2023-09-25",
        "price": 2.7
    },
    {
        "id": 157,
        "product_id": "516",
        "date": "2023-09-28",
        "price": 1.01
    },
    {
        "id": 158,
        "product_id": "516",
        "date": "2023-09-27",
        "price": 2.05
    },
    {
        "id": 159,
        "product_id": "516",
        "date": "2023-09-29",
        "price": 3.68
    },
    {
        "id": 160,
        "product_id": "516",
        "date": "2023-09-24",
        "price": 1.82
    },
    {
        "id": 161,
        "product_id": "516",
        "date": "2023-09-30",
        "price": 1.85
    },
    {
        "id": 162,
        "product_id": "1064",
        "date": "2023-09-26",
        "price": 3.36
    },
    {
        "id": 163,
        "product_id": "1064",
        "date": "2023-09-25",
        "price": 4.42
    },
    {
        "id": 164,
        "product_id": "1064",
        "date": "2023-09-28",
        "price": 1.28
    },
    {
        "id": 165,
        "product_id": "1064",
        "date": "2023-09-27",
        "price": 2.8
    },
    {
        "id": 166,
        "product_id": "1064",
        "date": "2023-09-29",
        "price": 1.04
    },
    {
        "id": 167,
        "product_id": "1064",
        "date": "2023-09-24",
        "price": 2.02
    },
    {
        "id": 168,
        "product_id": "1064",
        "date": "2023-09-30",
        "price": 1.42
    },
    {
        "id": 169,
        "product_id": "1143",
        "date": "2023-09-26",
        "price": 3.45
    },
    {
        "id": 170,
        "product_id": "1143",
        "date": "2023-09-25",
        "price": 1.98
    },
    {
        "id": 171,
        "product_id": "1143",
        "date": "2023-09-28",
        "price": 3.66
    },
    {
        "id": 172,
        "product_id": "1143",
        "date": "2023-09-27",
        "price": 2.46
    },
    {
        "id": 173,
        "product_id": "1143",
        "date": "2023-09-29",
        "price": 1.59
    },
    {
        "id": 174,
        "product_id": "1143",
        "date": "2023-09-24",
        "price": 3.43
    },
    {
        "id": 175,
        "product_id": "1143",
        "date": "2023-09-30",
        "price": 1.15
    },
    {
        "id": 176,
        "product_id": "1011",
        "date": "2023-09-26",
        "price": 2.12
    },
    {
        "id": 177,
        "product_id": "1011",
        "date": "2023-09-25",
        "price": 0.9
    },
    {
        "id": 178,
        "product_id": "1011",
        "date": "2023-09-28",
        "price": 1.88
    },
    {
        "id": 179,
        "product_id": "1011",
        "date": "2023-09-27",
        "price": 3.34
    },
    {
        "id": 180,
        "product_id": "1011",
        "date": "2023-09-29",
        "price": 2.81
    },
    {
        "id": 181,
        "product_id": "1011",
        "date": "2023-09-24",
        "price": 1.87
    },
    {
        "id": 182,
        "product_id": "1011",
        "date": "2023-09-30",
        "price": 4.39
    },
    {
        "id": 183,
        "product_id": "1022",
        "date": "2023-09-26",
        "price": 0.95
    },
    {
        "id": 184,
        "product_id": "1022",
        "date": "2023-09-25",
        "price": 3.96
    },
    {
        "id": 185,
        "product_id": "1022",
        "date": "2023-09-28",
        "price": 2.94
    },
    {
        "id": 186,
        "product_id": "1022",
        "date": "2023-09-27",
        "price": 1.94
    },
    {
        "id": 187,
        "product_id": "1022",
        "date": "2023-09-29",
        "price": 1.39
    },
    {
        "id": 188,
        "product_id": "1022",
        "date": "2023-09-24",
        "price": 2.97
    },
    {
        "id": 189,
        "product_id": "1022",
        "date": "2023-09-30",
        "price": 2.49
    },
    {
        "id": 190,
        "product_id": "1175",
        "date": "2023-09-26",
        "price": 1.64
    },
    {
        "id": 191,
        "product_id": "1175",
        "date": "2023-09-25",
        "price": 1.84
    },
    {
        "id": 192,
        "product_id": "1175",
        "date": "2023-09-28",
        "price": 1.75
    },
    {
        "id": 193,
        "product_id": "1175",
        "date": "2023-09-27",
        "price": 4.32
    },
    {
        "id": 194,
        "product_id": "1175",
        "date": "2023-09-29",
        "price": 4.23
    },
    {
        "id": 195,
        "product_id": "1175",
        "date": "2023-09-24",
        "price": 4.5
    },
    {
        "id": 196,
        "product_id": "1175",
        "date": "2023-09-30",
        "price": 3.56
    },
    {
        "id": 197,
        "product_id": "1301",
        "date": "2023-09-26",
        "price": 2.33
    },
    {
        "id": 198,
        "product_id": "1301",
        "date": "2023-09-25",
        "price": 3.72
    },
    {
        "id": 199,
        "product_id": "1301",
        "date": "2023-09-28",
        "price": 1.48
    },
    {
        "id": 200,
        "product_id": "1301",
        "date": "2023-09-27",
        "price": 2.9
    },
    {
        "id": 201,
        "product_id": "1301",
        "date": "2023-09-29",
        "price": 3.04
    },
    {
        "id": 202,
        "product_id": "1301",
        "date": "2023-09-24",
        "price": 4.0
    },
    {
        "id": 203,
        "product_id": "1301",
        "date": "2023-09-30",
        "price": 1.49
    },
    {
        "id": 204,
        "product_id": "1348",
        "date": "2023-09-26",
        "price": 1.73
    },
    {
        "id": 205,
        "product_id": "1348",
        "date": "2023-09-25",
        "price": 3.28
    },
    {
        "id": 206,
        "product_id": "1348",
        "date": "2023-09-28",
        "price": 3.73
    },
    {
        "id": 207,
        "product_id": "1348",
        "date": "2023-09-27",
        "price": 0.69
    },
    {
        "id": 208,
        "product_id": "1348",
        "date": "2023-09-29",
        "price": 2.69
    },
    {
        "id": 209,
        "product_id": "1348",
        "date": "2023-09-24",
        "price": 1.52
    },
    {
        "id": 210,
        "product_id": "1348",
        "date": "2023-09-30",
        "price": 3.09
    },
    {
        "id": 211,
        "product_id": "1077",
        "date": "2023-09-26",
        "price": 0.81
    },
    {
        "id": 212,
        "product_id": "1077",
        "date": "2023-09-25",
        "price": 3.04
    },
    {
        "id": 213,
        "product_id": "1077",
        "date": "2023-09-28",
        "price": 4.45
    },
    {
        "id": 214,
        "product_id": "1077",
        "date": "2023-09-27",
        "price": 2.75
    },
    {
        "id": 215,
        "product_id": "1077",
        "date": "2023-09-29",
        "price": 3.26
    },
    {
        "id": 216,
        "product_id": "1077",
        "date": "2023-09-24",
        "price": 1.35
    },
    {
        "id": 217,
        "product_id": "1077",
        "date": "2023-09-30",
        "price": 1.64
    },
    {
        "id": 218,
        "product_id": "1152",
        "date": "2023-09-26",
        "price": 0.85
    },
    {
        "id": 219,
        "product_id": "1152",
        "date": "2023-09-25",
        "price": 3.29
    },
    {
        "id": 220,
        "product_id": "1152",
        "date": "2023-09-28",
        "price": 2.85
    },
    {
        "id": 221,
        "product_id": "1152",
        "date": "2023-09-27",
        "price": 0.51
    },
    {
        "id": 222,
        "product_id": "1152",
        "date": "2023-09-29",
        "price": 2.53
    },
    {
        "id": 223,
        "product_id": "1152",
        "date": "2023-09-24",
        "price": 1.66
    },
    {
        "id": 224,
        "product_id": "1152",
        "date": "2023-09-30",
        "price": 1.39
    },
    {
        "id": 225,
        "product_id": "1153",
        "date": "2023-09-26",
        "price": 3.52
    },
    {
        "id": 226,
        "product_id": "1153",
        "date": "2023-09-25",
        "price": 2.32
    },
    {
        "id": 227,
        "product_id": "1153",
        "date": "2023-09-28",
        "price": 3.91
    },
    {
        "id": 228,
        "product_id": "1153",
        "date": "2023-09-27",
        "price": 4.41
    },
    {
        "id": 229,
        "product_id": "1153",
        "date": "2023-09-29",
        "price": 2.0
    },
    {
        "id": 230,
        "product_id": "1153",
        "date": "2023-09-24",
        "price": 2.15
    },
    {
        "id": 231,
        "product_id": "1153",
        "date": "2023-09-30",
        "price": 3.42
    },
    {
        "id": 232,
        "product_id": "1322",
        "date": "2023-09-26",
        "price": 3.56
    },
    {
        "id": 233,
        "product_id": "1322",
        "date": "2023-09-25",
        "price": 1.12
    },
    {
        "id": 234,
        "product_id": "1322",
        "date": "2023-09-28",
        "price": 0.7
    },
    {
        "id": 235,
        "product_id": "1322",
        "date": "2023-09-27",
        "price": 1.1
    },
    {
        "id": 236,
        "product_id": "1322",
        "date": "2023-09-29",
        "price": 1.89
    },
    {
        "id": 237,
        "product_id": "1322",
        "date": "2023-09-24",
        "price": 2.02
    },
    {
        "id": 238,
        "product_id": "1322",
        "date": "2023-09-30",
        "price": 3.58
    },
    {
        "id": 239,
        "product_id": "1332",
        "date": "2023-09-26",
        "price": 3.45
    },
    {
        "id": 240,
        "product_id": "1332",
        "date": "2023-09-25",
        "price": 1.22
    },
    {
        "id": 241,
        "product_id": "1332",
        "date": "2023-09-28",
        "price": 4.16
    },
    {
        "id": 242,
        "product_id": "1332",
        "date": "2023-09-27",
        "price": 2.59
    },
    {
        "id": 243,
        "product_id": "1332",
        "date": "2023-09-29",
        "price": 0.99
    },
    {
        "id": 244,
        "product_id": "1332",
        "date": "2023-09-24",
        "price": 3.13
    },
    {
        "id": 245,
        "product_id": "1332",
        "date": "2023-09-30",
        "price": 2.62
    },
    {
        "id": 246,
        "product_id": "1178",
        "date": "2023-09-26",
        "price": 1.02
    },
    {
        "id": 247,
        "product_id": "1178",
        "date": "2023-09-25",
        "price": 1.66
    },
    {
        "id": 248,
        "product_id": "1178",
        "date": "2023-09-28",
        "price": 4.22
    },
    {
        "id": 249,
        "product_id": "1178",
        "date": "2023-09-27",
        "price": 1.65
    },
    {
        "id": 250,
        "product_id": "1178",
        "date": "2023-09-29",
        "price": 1.31
    },
    {
        "id": 251,
        "product_id": "1178",
        "date": "2023-09-24",
        "price": 1.66
    },
    {
        "id": 252,
        "product_id": "1178",
        "date": "2023-09-30",
        "price": 1.88
    },
    {
        "id": 253,
        "product_id": "1203",
        "date": "2023-09-26",
        "price": 2.9
    },
    {
        "id": 254,
        "product_id": "1203",
        "date": "2023-09-25",
        "price": 4.08
    },
    {
        "id": 255,
        "product_id": "1203",
        "date": "2023-09-28",
        "price": 0.67
    },
    {
        "id": 256,
        "product_id": "1203",
        "date": "2023-09-27",
        "price": 4.06
    },
    {
        "id": 257,
        "product_id": "1203",
        "date": "2023-09-29",
        "price": 1.11
    },
    {
        "id": 258,
        "product_id": "1203",
        "date": "2023-09-24",
        "price": 2.25
    },
    {
        "id": 259,
        "product_id": "1203",
        "date": "2023-09-30",
        "price": 0.84
    },
    {
        "id": 260,
        "product_id": "1266",
        "date": "2023-09-26",
        "price": 2.65
    },
    {
        "id": 261,
        "product_id": "1266",
        "date": "2023-09-25",
        "price": 1.81
    },
    {
        "id": 262,
        "product_id": "1266",
        "date": "2023-09-28",
        "price": 2.45
    },
    {
        "id": 263,
        "product_id": "1266",
        "date": "2023-09-27",
        "price": 0.58
    },
    {
        "id": 264,
        "product_id": "1266",
        "date": "2023-09-29",
        "price": 2.23
    },
    {
        "id": 265,
        "product_id": "1266",
        "date": "2023-09-24",
        "price": 2.43
    },
    {
        "id": 266,
        "product_id": "1266",
        "date": "2023-09-30",
        "price": 0.53
    },
    {
        "id": 267,
        "product_id": "1305",
        "date": "2023-09-26",
        "price": 3.12
    },
    {
        "id": 268,
        "product_id": "1305",
        "date": "2023-09-25",
        "price": 3.59
    },
    {
        "id": 269,
        "product_id": "1305",
        "date": "2023-09-28",
        "price": 4.25
    },
    {
        "id": 270,
        "product_id": "1305",
        "date": "2023-09-27",
        "price": 1.79
    },
    {
        "id": 271,
        "product_id": "1305",
        "date": "2023-09-29",
        "price": 2.52
    },
    {
        "id": 272,
        "product_id": "1305",
        "date": "2023-09-24",
        "price": 1.7
    },
    {
        "id": 273,
        "product_id": "1305",
        "date": "2023-09-30",
        "price": 4.27
    },
    {
        "id": 274,
        "product_id": "1337",
        "date": "2023-09-26",
        "price": 3.25
    },
    {
        "id": 275,
        "product_id": "1337",
        "date": "2023-09-25",
        "price": 4.47
    },
    {
        "id": 276,
        "product_id": "1337",
        "date": "2023-09-28",
        "price": 1.62
    },
    {
        "id": 277,
        "product_id": "1337",
        "date": "2023-09-27",
        "price": 2.8
    },
    {
        "id": 278,
        "product_id": "1337",
        "date": "2023-09-29",
        "price": 3.62
    },
    {
        "id": 279,
        "product_id": "1337",
        "date": "2023-09-24",
        "price": 2.57
    },
    {
        "id": 280,
        "product_id": "1337",
        "date": "2023-09-30",
        "price": 2.09
    }
]
